{
    "crime": "Get IMSI and the ISO country code",
    "permission": [],
    "api": [
        {
            "descriptor": "()Ljava/lang/String;",
            "class": "Landroid/telephony/TelephonyManager;",
            "method": "getSubscriberId"
        },
        {
            "descriptor": "()Ljava/lang/String;",
            "class": "Landroid/telephony/TelephonyManager;",
            "method": "getNetworkCountryIso"
        }
    ],
    "score": 1,
    "label": [
        "collection",
        "telephony"
    ]
}